com_vitalai_haley_domain/__init__.py
com_vitalai_haley_domain/domain-ontology/haley-0.1.0.owl
com_vitalai_haley_domain/model/AgentDeveloper.py
com_vitalai_haley_domain/model/AgentDeveloper.pyi
com_vitalai_haley_domain/model/ChannelOrgType.py
com_vitalai_haley_domain/model/ChannelOrgType.pyi
com_vitalai_haley_domain/model/CloudAgent.py
com_vitalai_haley_domain/model/CloudAgent.pyi
com_vitalai_haley_domain/model/CloudApp.py
com_vitalai_haley_domain/model/CloudApp.pyi
com_vitalai_haley_domain/model/CloudAppActivity.py
com_vitalai_haley_domain/model/CloudAppActivity.pyi
com_vitalai_haley_domain/model/CloudAppDeployment.py
com_vitalai_haley_domain/model/CloudAppDeployment.pyi
com_vitalai_haley_domain/model/CloudAppLimits.py
com_vitalai_haley_domain/model/CloudAppLimits.pyi
com_vitalai_haley_domain/model/CloudBucket.py
com_vitalai_haley_domain/model/CloudBucket.pyi
com_vitalai_haley_domain/model/CloudCertificate.py
com_vitalai_haley_domain/model/CloudCertificate.pyi
com_vitalai_haley_domain/model/CloudCertificateStatus.py
com_vitalai_haley_domain/model/CloudCertificateStatus.pyi
com_vitalai_haley_domain/model/CloudCluster.py
com_vitalai_haley_domain/model/CloudCluster.pyi
com_vitalai_haley_domain/model/CloudCodePath.py
com_vitalai_haley_domain/model/CloudCodePath.pyi
com_vitalai_haley_domain/model/CloudCodePathType.py
com_vitalai_haley_domain/model/CloudCodePathType.pyi
com_vitalai_haley_domain/model/CloudCodeRepo.py
com_vitalai_haley_domain/model/CloudCodeRepo.pyi
com_vitalai_haley_domain/model/CloudContainer.py
com_vitalai_haley_domain/model/CloudContainer.pyi
com_vitalai_haley_domain/model/CloudContainerRepo.py
com_vitalai_haley_domain/model/CloudContainerRepo.pyi
com_vitalai_haley_domain/model/CloudContentDistribution.py
com_vitalai_haley_domain/model/CloudContentDistribution.pyi
com_vitalai_haley_domain/model/CloudDeploymentMessage.py
com_vitalai_haley_domain/model/CloudDeploymentMessage.pyi
com_vitalai_haley_domain/model/CloudDeploymentScript.py
vital_ai_haley-0.1.8.dist-info/METADATA
vital_ai_haley-0.1.8.dist-info/WHEEL
vital_ai_haley-0.1.8.dist-info/entry_points.txt
vital_ai_haley-0.1.8.dist-info/top_level.txt
vital_ai_haley-0.1.8.dist-info/RECORD
